{
  "clusters": [
    {
      "cluster_id": 1,
      "theme": "デジタル時代の人間性",
      "summary": "デジタル時代における人間性の維持と再考は、持続可能な社会を構築するために不可欠であり、オリヴァー・サックスの問いかけを再考することの重要性を示している。",
      "keywords": [
        "人間性",
        "デジタル時代",
        "オリヴァー・サックス",
        "持続可能な社会"
      ]
    },
    {
      "cluster_id": 2,
      "theme": "デジタル環境への適応",
      "summary": "デジタル技術の進展に対応し、変化する環境に適応していく必要性。",
      "keywords": [
        "デジタル環境",
        "適応",
        "技術進展"
      ]
    },
    {
      "cluster_id": 3,
      "theme": "人間性の保持",
      "summary": "デジタル化が進む社会においても、人間らしさを失わずに維持することの重要性。",
      "keywords": [
        "人間性",
        "保持",
        "デジタル化"
      ]
    },
    {
      "cluster_id": 4,
      "theme": "健全なデジタル利用習慣の育成",
      "summary": "デジタル技術の利用において、心身の健康を損なわない、バランスの取れた利用習慣を身につける必要性。",
      "keywords": [
        "デジタル利用",
        "習慣",
        "健全性"
      ]
    },
    {
      "cluster_id": 5,
      "theme": "デジタルウェルビーイングの確立",
      "summary": "デジタル技術を活用しながら、精神的、肉体的、社会的に良好な状態を維持・向上させることの重要性。",
      "keywords": [
        "デジタルウェルビーイング",
        "幸福",
        "心身の健康"
      ]
    }
  ]
}