{
  "knowledge_entries": [
    {
      "theme": "オリヴァー・サックスの警鐘と人間性",
      "tweet": "オリヴァー・サックスは、技術が進む現代こそ人間性への深い理解が不可欠だと訴えました。患者の物語に耳を傾け、共感することで、医療や社会における人間性の尊重を促した彼の警鐘は、今も私たちに響き続けています。",
      "created_at": "2025-08-09T10:00:46.472176"
    },
    {
      "theme": "デジタル・ウェルビーイングの戦略的構築の定義",
      "tweet": "デジタル・ウェルビーイングとは、デジタル技術との上手な付き合い方を見つけ、心身の健康と生活の質を高める戦略です。自己認識を高め、意図的な利用を心がけましょう。 #デジタルウェルビーイング #ウェルビーイング",
      "created_at": "2025-08-09T11:00:48.457514"
    },
    {
      "theme": "オリヴァー・サックスの警鐘と人間性",
      "tweet": "オリヴァー・サックスは、テクノロジーが進化する現代において、人間性や人間らしさが失われることへの警鐘を鳴らしました。患者の物語に耳を傾け、人間的なケアを重視することの重要性を訴えかけます。",
      "created_at": "2025-08-09T12:14:16.795488"
    },
    {
      "theme": "デジタル環境における自己認識の重要性",
      "tweet": "デジタル環境での自己認識は重要です。SNS利用時間を意識したり、通知をオフにしたりして、デジタル・ウェルビーイングを高めましょう。自分とデジタルとの付き合い方を見直しませんか？",
      "created_at": "2025-08-09T13:21:40.316375"
    },
    {
      "theme": "デジタル環境における自己認識の重要性",
      "tweet": "デジタル環境での自己認識は重要です。利用時間やコンテンツを意識的にコントロールし、デジタルリスクへの対策を講じることが、健全なデジタルライフにつながります。#デジタルウェルビーイング",
      "created_at": "2025-08-09T14:00:44.920937"
    }
  ]
}